spotify_monitor.py
spotify_monitor-2.7.dist-info/licenses/LICENSE
spotify_monitor-2.7.dist-info/METADATA
spotify_monitor-2.7.dist-info/WHEEL
spotify_monitor-2.7.dist-info/entry_points.txt
spotify_monitor-2.7.dist-info/top_level.txt
spotify_monitor-2.7.dist-info/RECORD
