Metadata-Version: 2.4
Name: spotify_monitor
Version: 2.7
Summary: Tool implementing real-time tracking of Spotify friends music activity
Author-email: Michal Szymanski <misiektoja-pypi@rm-rf.ninja>
License-Expression: GPL-3.0-or-later
Project-URL: Homepage, https://github.com/misiektoja/spotify_monitor
Project-URL: Source, https://github.com/misiektoja/spotify_monitor
Project-URL: Changelog, https://github.com/misiektoja/spotify_monitor/blob/main/RELEASE_NOTES.md
Keywords: spotify,monitoring,tracking,real-time,friend-activity,osint
Classifier: Programming Language :: Python :: 3
Classifier: Operating System :: OS Independent
Classifier: Operating System :: Microsoft :: Windows
Classifier: Operating System :: POSIX :: Linux
Classifier: Operating System :: MacOS :: MacOS X
Requires-Python: >=3.6
License-File: LICENSE
Requires-Dist: requests>=2.0
Requires-Dist: python-dateutil>=2.8
Requires-Dist: urllib3>=2.0.7
Requires-Dist: pyotp>=2.9.0
Requires-Dist: python-dotenv>=0.19
Requires-Dist: wcwidth>=0.2.7
Requires-Dist: spotipy>=2.24.0
Dynamic: license-file
